k3project_generator/__init__.py
k3project_generator/genproject.py
k3project_generator/main/__init__.py
k3project_generator/main/generate_project.py
k3project_generator/resources/__init__.py
k3project_generator/resources/dummy__version.py
k3project_generator/resources/dummy_lib.py
k3project_generator/resources/dummy_main.py
k3project_generator/resources/dummy_setup.py
k3project_generator/resources/dummy_test_.py
k3project_generator/resources/dummy_test_readme.md
k3project_generator/resources/main__init__.py
k3project_generator/resources/licences/APACHE_2_0.txt
k3project_generator/resources/licences/APACHE_2_0_NOTICE.txt
k3project_generator/resources/licences/GPLv3.txt
k3project_generator/resources/licences/MIT.txt
k3project_generator/resources/licences/__init__.py
k3project_generator-0.3.dist-info/LICENSE
k3project_generator-0.3.dist-info/METADATA
k3project_generator-0.3.dist-info/WHEEL
k3project_generator-0.3.dist-info/entry_points.txt
k3project_generator-0.3.dist-info/top_level.txt
k3project_generator-0.3.dist-info/RECORD
